{
  "kind": "youtube#searchListResponse",
  "etag": "\"m2yskBQFythfE4irbTIeOgYYfBU/TBfjSpBktnAKr-ogzx8SPYqHDLU\"",
  "nextPageToken": "CAIQAA",
  "regionCode": "NO",
  "pageInfo": {
    "totalResults": 1000000,
    "resultsPerPage": 2
  },
  "items": [
    {
      "kind": "youtube#searchResult",
      "etag": "\"m2yskBQFythfE4irbTIeOgYYfBU/2rQyWVouu7LOdsMpHt_A3RriHGs\"",
      "id": {
        "kind": "youtube#video",
        "videoId": "bDYiAVhxe3E"
      },
      "snippet": {
        "publishedAt": "2010-08-03T21:59:33.000Z",
        "channelId": "UCiiaphPc2THqNDS4SSc-tIw",
        "title": "Discovery- Can You Discover.WMV",
        "description": "Such an amazing rendition of the ra-ra-riot song...",
        "thumbnails": {
          "default": {
            "url": "https://i.ytimg.com/vi/bDYiAVhxe3E/default.jpg",
            "width": 120,
            "height": 90
          },
          "medium": {
            "url": "https://i.ytimg.com/vi/bDYiAVhxe3E/mqdefault.jpg",
            "width": 320,
            "height": 180
          },
          "high": {
            "url": "https://i.ytimg.com/vi/bDYiAVhxe3E/hqdefault.jpg",
            "width": 480,
            "height": 360
          }
        },
        "channelTitle": "Brodi Petitt",
        "liveBroadcastContent": "none"
      }
    },
    {
      "kind": "youtube#searchResult",
      "etag": "\"m2yskBQFythfE4irbTIeOgYYfBU/WKWQnEWty0J_OpbRVm30lsbp1V0\"",
      "id": {
        "kind": "youtube#video",
        "videoId": "XpfOjJW_Rjs"
      },
      "snippet": {
        "publishedAt": "2010-09-20T01:57:35.000Z",
        "channelId": "UCxFzhAahO07Oi8zRfV8alww",
        "title": "Can You Discover? By Discovery",
        "description": "Can You Discover? By Discovery.",
        "thumbnails": {
          "default": {
            "url": "https://i.ytimg.com/vi/XpfOjJW_Rjs/default.jpg",
            "width": 120,
            "height": 90
          },
          "medium": {
            "url": "https://i.ytimg.com/vi/XpfOjJW_Rjs/mqdefault.jpg",
            "width": 320,
            "height": 180
          },
          "high": {
            "url": "https://i.ytimg.com/vi/XpfOjJW_Rjs/hqdefault.jpg",
            "width": 480,
            "height": 360
          }
        },
        "channelTitle": "lcm603",
        "liveBroadcastContent": "none"
      }
    }
  ]
}
